{"code": 200, "data": {"deviceName": "TEST SOURCE", "deviceId": "200009", "deviceBrand": "", "deviceSeries": "", "deviceModel": "TEST SOURCE", "contentVersion": 1, "agreementVersion": "", "pixelsLengthX": 1, "pixelsLengthY": 1, "dimItem": "50", "dimDelay": "2", "control": ["CTRL_BT_MESH"], "luminance": "LT_100", "fan": ["FAN_FULL", "FAN_OFF"], "flmModeList": [{"modeName": "FLM_CCT", "cmd": "02", "remark": "色温模式", "tip": "", "cmdList": [{"id": 603, "modeId": 2, "cmdName": "IGNORE", "cmd": "0B", "remark": "OPT_SEQUENCE", "byteCount": 1}, {"id": 604, "modeId": 2, "cmdName": "OPT_DIM", "cmd": "0032", "remark": "OPT_DIM", "byteCount": 2}, {"id": 605, "modeId": 2, "cmdName": "IGNORE", "cmd": "02", "remark": "FLM_CCT", "byteCount": 1}, {"id": 606, "modeId": 2, "cmdName": "SLM_CCT", "cmd": "02", "remark": "SLM_CCT", "byteCount": 1}, {"id": 607, "modeId": 2, "cmdName": "OUTPUT_MODE", "cmd": "01", "remark": "OUTPUT_MODE", "byteCount": 1}, {"id": 608, "modeId": 2, "cmdName": "OPT_CCT", "cmd": "15e0", "remark": "OPT_CCT", "byteCount": 2}, {"id": 609, "modeId": 2, "cmdName": "OPT_GM", "cmd": "0000", "remark": "OPT_GM", "byteCount": 2}, {"id": 610, "modeId": 2, "cmdName": "SOURCE_MODE", "cmd": "02", "remark": "SOURCE_MODE", "byteCount": 1}], "firstControls": [{"id": 3, "parentId": 2, "uuid": "0620375c-9eb0-11ec-8c14-00163e1b6f58", "controlName": "SLM_CCT", "controlType": "box", "selectIndex": 0, "cmd": "", "remark": "色温灯光模式", "tip": "", "elements": {}, "cmdList": [], "controls": [{"id": 4, "parentId": 3, "uuid": "0620379d-9eb0-11ec-8c14-00163e1b6f58", "controlName": "SLM_CCT_STANDARD", "controlType": "", "selectIndex": 0, "cmd": "02", "remark": "标准模式", "tip": "", "elements": {}, "cmdList": [{"id": 1, "modeId": 4, "cmdName": "IGNORE", "cmd": "0B", "remark": "OPT_SEQUENCE", "byteCount": 1}, {"id": 2, "modeId": 4, "cmdName": "OPT_DIM", "cmd": "0032", "remark": "OPT_DIM", "byteCount": 2}, {"id": 3, "modeId": 4, "cmdName": "IGNORE", "cmd": "02", "remark": "FLM_CCT", "byteCount": 1}, {"id": 4, "modeId": 4, "cmdName": "IGNORE", "cmd": "02", "remark": "SLM_CCT", "byteCount": 1}, {"id": 5, "modeId": 4, "cmdName": "OUTPUT_MODE", "cmd": "01", "remark": "OUTPUT_MODE", "byteCount": 1}, {"id": 6, "modeId": 4, "cmdName": "OPT_CCT", "cmd": "15e0", "remark": "OPT_CCT", "byteCount": 2}, {"id": 7, "modeId": 4, "cmdName": "OPT_GM", "cmd": "0000", "remark": "0000", "byteCount": 2}, {"id": 8, "modeId": 4, "cmdName": "SOURCE_MODE", "cmd": "02", "remark": "SOURCE_MODE", "byteCount": 1}], "controls": [{"id": 815, "parentId": 4, "uuid": "734dfce0-ae36-11ec-8c14-00163e1b6f58", "controlName": "SOURCE_MODE", "controlType": "box", "selectIndex": 0, "cmd": "08", "remark": "柔硬光切换", "tip": "", "elements": {}, "cmdList": [], "controls": [{"id": 816, "parentId": 815, "uuid": "8d801412-ae36-11ec-8c14-00163e1b6f58", "controlName": "SOUR_MIX_HARD", "controlType": "", "selectIndex": 0, "cmd": "02", "remark": "硬光模式", "tip": "", "elements": {}, "cmdList": [], "controls": []}, {"id": 817, "parentId": 815, "uuid": "9a49b753-ae36-11ec-8c14-00163e1b6f58", "controlName": "SOUR_MIX_SOFT", "controlType": "", "selectIndex": 0, "cmd": "03", "remark": "柔光模式", "tip": "", "elements": {}, "cmdList": [], "controls": []}]}, {"id": 6, "parentId": 4, "uuid": "06203811-9eb0-11ec-8c14-00163e1b6f58", "controlName": "OPT_DIM", "controlType": "slip", "selectIndex": 0, "cmd": "01", "remark": "亮度", "tip": "", "elements": {"max": "100", "min": "0", "step": "1", "item": "50", "toggle": "1", "delay": "1"}, "cmdList": [], "controls": []}, {"id": 7, "parentId": 4, "uuid": "0620384c-9eb0-11ec-8c14-00163e1b6f58", "controlName": "OPT_CCT", "controlType": "slip", "selectIndex": 0, "cmd": "03", "remark": "色温", "tip": "", "elements": {"max": "7500", "min": "2700", "step": "100", "item": "5600"}, "cmdList": [], "controls": []}, {"id": 8, "parentId": 4, "uuid": "06203881-9eb0-11ec-8c14-00163e1b6f58", "controlName": "OPT_GM", "controlType": "slip", "selectIndex": 0, "cmd": "04", "remark": "红绿平衡", "tip": "", "elements": {"max": "100", "min": "-100", "step": "1", "item": "0"}, "cmdList": [], "controls": []}]}]}]}], "groupModeList": [{"modeName": "FLM_GROUP_EFFECT", "cmd": "09", "remark": "群组特效模式", "tip": "", "cmdList": [], "firstControls": [{"id": 537, "parentId": 536, "uuid": "66f9b8ba-9f84-11ec-8c14-00163e1b6f58", "controlName": "SLM_MENU", "controlType": "slm", "selectIndex": 0, "cmd": "", "remark": "", "tip": "", "elements": {}, "cmdList": [], "controls": [{"id": 538, "parentId": 537, "uuid": "82a01186-9f84-11ec-8c14-00163e1b6f58", "controlName": "SLM_GROUP_HUE_LOOP", "controlType": "", "selectIndex": 0, "cmd": "13", "remark": "颜色循环", "tip": "", "elements": {}, "cmdList": [{"id": 430, "modeId": 538, "cmdName": "IGNORE", "cmd": "1D", "remark": "OPT_SEQUENCE", "byteCount": 1}, {"id": 431, "modeId": 538, "cmdName": "OPT_DIM", "cmd": "0032", "remark": "OPT_DIM", "byteCount": 2}, {"id": 432, "modeId": 538, "cmdName": "IGNORE", "cmd": "09", "remark": "FLM_GROUP_EFFECT", "byteCount": 1}, {"id": 433, "modeId": 538, "cmdName": "IGNORE", "cmd": "13", "remark": "SLM_GROUP_HUE_LOOP", "byteCount": 1}, {"id": 434, "modeId": 538, "cmdName": "OPT_POSITION", "cmd": "000000000000", "remark": "OPT_POSITION", "byteCount": 6}, {"id": 435, "modeId": 538, "cmdName": "OPT_HUE1", "cmd": "0000", "remark": "OPT_HUE1", "byteCount": 2}, {"id": 436, "modeId": 538, "cmdName": "OPT_HUE2", "cmd": "0168", "remark": "OPT_HUE2", "byteCount": 2}, {"id": 437, "modeId": 538, "cmdName": "OPT_SAT", "cmd": "64", "remark": "OPT_SAT", "byteCount": 1}, {"id": 438, "modeId": 538, "cmdName": "OPT_SPEED_TIME", "cmd": "08", "remark": "OPT_SPEED_TIME", "byteCount": 1}, {"id": 439, "modeId": 538, "cmdName": "OPT_CYCLE", "cmd": "02", "remark": "OPT_CYCLE", "byteCount": 1}, {"id": 440, "modeId": 538, "cmdName": "OPT_ADD_ON", "cmd": "01", "remark": "OPT_ADD_ON", "byteCount": 1}, {"id": 441, "modeId": 538, "cmdName": "OPT_INTERVALS", "cmd": "03E8", "remark": "OPT_INTERVALS", "byteCount": 2}, {"id": 442, "modeId": 538, "cmdName": "OPT_RATIO", "cmd": "32", "remark": "OPT_RATIO", "byteCount": 1}, {"id": 443, "modeId": 538, "cmdName": "OPT_PULSES", "cmd": "28", "remark": "OPT_PULSES", "byteCount": 1}, {"id": 444, "modeId": 538, "cmdName": "OPT_SPEED_ADD", "cmd": "32", "remark": "OPT_SPEED_ADD", "byteCount": 1}, {"id": 445, "modeId": 538, "cmdName": "OPT_GROUP_EFFECT", "cmd": "01", "remark": "OPT_GROUP_EFFECT", "byteCount": 1}, {"id": 446, "modeId": 538, "cmdName": "OPT_DELAY_TIME", "cmd": "05", "remark": "OPT_DELAY_TIME", "byteCount": 1}, {"id": 447, "modeId": 538, "cmdName": "OPT_DIRECTION", "cmd": "01", "remark": "OPT_DIRECTION", "byteCount": 1}, {"id": 448, "modeId": 538, "cmdName": "OPT_SYMMETRY", "cmd": "01", "remark": "OPT_SYMMETRY", "byteCount": 1}, {"id": 449, "modeId": 538, "cmdName": "OPT_RANDOM", "cmd": "32", "remark": "OPT_RANDOM", "byteCount": 1}], "controls": [{"id": 539, "parentId": 538, "uuid": "9b652760-9f85-11ec-8c14-00163e1b6f58", "controlName": "OPT_DIM", "controlType": "slip", "selectIndex": 0, "cmd": "01", "remark": "亮度", "tip": "", "elements": {"max": "100", "min": "0", "step": "1", "item": "50", "toggle": "1"}, "cmdList": [], "controls": []}, {"id": 540, "parentId": 538, "uuid": "aef26b4f-9f85-11ec-8c14-00163e1b6f58", "controlName": "OPT_HUE_RANGE", "controlType": "doubleSlip", "selectIndex": 0, "cmd": "", "remark": "色相范围", "tip": "", "elements": {"max": "360", "min": "0", "step": "1", "maxItem": "360", "minItem": "0"}, "cmdList": [], "controls": []}, {"id": 541, "parentId": 538, "uuid": "c391436f-9f85-11ec-8c14-00163e1b6f58", "controlName": "OPT_SAT", "controlType": "slip", "selectIndex": 0, "cmd": "0C", "remark": "饱和度", "tip": "", "elements": {"max": "100", "min": "0", "step": "1", "item": "100"}, "cmdList": [], "controls": []}, {"id": 542, "parentId": 538, "uuid": "d4e0becc-9f85-11ec-8c14-00163e1b6f58", "controlName": "OPT_SPEED_TIME", "controlType": "slip", "selectIndex": 0, "cmd": "54", "remark": "速度", "tip": "", "elements": {"max": "30", "min": "2", "step": "1", "item": "8"}, "cmdList": [], "controls": []}, {"id": 543, "parentId": 538, "uuid": "e5994e86-9f85-11ec-8c14-00163e1b6f58", "controlName": "OPT_CYCLE", "controlType": "box", "selectIndex": 1, "cmd": "19", "remark": "循环", "tip": "", "elements": {}, "cmdList": [], "controls": [{"id": 544, "parentId": 543, "uuid": "ffb87e82-9f85-11ec-8c14-00163e1b6f58", "controlName": "ONE_WAY", "controlType": "", "selectIndex": 0, "cmd": "01", "remark": "单向循环", "tip": "", "elements": {}, "cmdList": [], "controls": []}, {"id": 545, "parentId": 543, "uuid": "0c5a6164-9f86-11ec-8c14-00163e1b6f58", "controlName": "TWO_WAY", "controlType": "", "selectIndex": 0, "cmd": "02", "remark": "双向循环", "tip": "", "elements": {}, "cmdList": [], "controls": []}, {"id": 546, "parentId": 543, "uuid": "11f55de0-9f86-11ec-8c14-00163e1b6f58", "controlName": "REVERSE", "controlType": "", "selectIndex": 0, "cmd": "03", "remark": "反向循环", "tip": "", "elements": {}, "cmdList": [], "controls": []}]}, {"id": 547, "parentId": 538, "uuid": "1a9e5b98-9f86-11ec-8c14-00163e1b6f58", "controlName": "DIVIDER", "controlType": "divider", "selectIndex": 0, "cmd": "", "remark": "分割线", "tip": "", "elements": {}, "cmdList": [], "controls": []}, {"id": 548, "parentId": 538, "uuid": "30d23557-9f86-11ec-8c14-00163e1b6f58", "controlName": "OPT_GROUP_EFFECT", "controlType": "box", "selectIndex": 0, "cmd": "59", "remark": "群组特效", "tip": "", "elements": {}, "cmdList": [], "controls": [{"id": 549, "parentId": 548, "uuid": "43d8840f-9f86-11ec-8c14-00163e1b6f58", "controlName": "DELAY", "controlType": "", "selectIndex": 0, "cmd": "01", "remark": "延迟", "tip": "", "elements": {}, "cmdList": [], "controls": [{"id": 552, "parentId": 549, "uuid": "5e6db4f0-9f86-11ec-8c14-00163e1b6f58", "controlName": "OPT_DELAY_TIME", "controlType": "slip", "selectIndex": 0, "cmd": "42", "remark": "延迟", "tip": "", "elements": {"max": "20", "min": "1", "step": "1", "item": "5"}, "cmdList": [], "controls": []}, {"id": 553, "parentId": 549, "uuid": "6e8bd46f-9f86-11ec-8c14-00163e1b6f58", "controlName": "OPT_DIRECTION", "controlType": "box", "selectIndex": 0, "cmd": "43", "remark": "方向", "tip": "", "elements": {}, "cmdList": [], "controls": [{"id": 554, "parentId": 553, "uuid": "788c57cf-9f86-11ec-8c14-00163e1b6f58", "controlName": "FORWARD", "controlType": "", "selectIndex": 0, "cmd": "01", "remark": "正向", "tip": "", "elements": {}, "cmdList": [], "controls": []}, {"id": 555, "parentId": 553, "uuid": "7f8ae6e9-9f86-11ec-8c14-00163e1b6f58", "controlName": "BACKWARD", "controlType": "", "selectIndex": 0, "cmd": "02", "remark": "反向", "tip": "", "elements": {}, "cmdList": [], "controls": []}]}, {"id": 556, "parentId": 549, "uuid": "8bbf57e2-9f86-11ec-8c14-00163e1b6f58", "controlName": "OPT_SYMMETRY", "controlType": "box", "selectIndex": 0, "cmd": "44", "remark": "对称", "tip": "", "elements": {}, "cmdList": [], "controls": [{"id": 557, "parentId": 556, "uuid": "93210180-9f86-11ec-8c14-00163e1b6f58", "controlName": "OFF", "controlType": "", "selectIndex": 0, "cmd": "01", "remark": "关闭", "tip": "", "elements": {}, "cmdList": [], "controls": []}, {"id": 558, "parentId": 556, "uuid": "99713a15-9f86-11ec-8c14-00163e1b6f58", "controlName": "ON", "controlType": "", "selectIndex": 0, "cmd": "00", "remark": "开启", "tip": "", "elements": {}, "cmdList": [], "controls": []}]}]}, {"id": 550, "parentId": 548, "uuid": "4a02bf34-9f86-11ec-8c14-00163e1b6f58", "controlName": "RANDOM", "controlType": "", "selectIndex": 0, "cmd": "02", "remark": "随机", "tip": "", "elements": {}, "cmdList": [], "controls": [{"id": 857, "parentId": 550, "uuid": "df249090-c554-11ec-8c14-00163e1b6f58", "controlName": "OPT_RANDOM", "controlType": "slip", "selectIndex": 0, "cmd": "45", "remark": "随机", "tip": "", "elements": {"max": "100", "min": "1", "step": "1", "item": "50"}, "cmdList": [], "controls": []}]}, {"id": 551, "parentId": 548, "uuid": "54795666-9f86-11ec-8c14-00163e1b6f58", "controlName": "ALTERNATE", "controlType": "", "selectIndex": 0, "cmd": "03", "remark": "交替", "tip": "", "elements": {}, "cmdList": [], "controls": []}]}, {"id": 844, "parentId": 538, "uuid": "7aa3b884-b560-11ec-8c14-00163e1b6f58", "controlName": "DIVIDER", "controlType": "divider", "selectIndex": 0, "cmd": "", "remark": "分割线", "tip": "", "elements": {}, "cmdList": [], "controls": []}, {"id": 559, "parentId": 538, "uuid": "afbaa8b4-9f86-11ec-8c14-00163e1b6f58", "controlName": "OPT_ADD_ON", "controlType": "box", "selectIndex": 0, "cmd": "1A", "remark": "附加效果", "tip": "", "elements": {}, "cmdList": [], "controls": [{"id": 560, "parentId": 559, "uuid": "bb214090-9f86-11ec-8c14-00163e1b6f58", "controlName": "ADD_OFF", "controlType": "", "selectIndex": 0, "cmd": "01", "remark": "关闭", "tip": "", "elements": {}, "cmdList": [], "controls": []}, {"id": 561, "parentId": 559, "uuid": "c1703e88-9f86-11ec-8c14-00163e1b6f58", "controlName": "ADD_FLASH", "controlType": "", "selectIndex": 0, "cmd": "02", "remark": "闪烁", "tip": "", "elements": {}, "cmdList": [], "controls": [{"id": 564, "parentId": 561, "uuid": "db262b1b-9f86-11ec-8c14-00163e1b6f58", "controlName": "OPT_INTERVALS", "controlType": "slip", "selectIndex": 0, "cmd": "1B", "remark": "间隔", "tip": "", "elements": {"max": "10000", "min": "100", "step": "100", "item": "1000"}, "cmdList": [], "controls": []}, {"id": 565, "parentId": 561, "uuid": "ec90c1ad-9f86-11ec-8c14-00163e1b6f58", "controlName": "OPT_RATIO", "controlType": "slip", "selectIndex": 0, "cmd": "1C", "remark": "亮暗比例", "tip": "", "elements": {"max": "100", "min": "0", "step": "1", "item": "50"}, "cmdList": [], "controls": []}]}, {"id": 562, "parentId": 559, "uuid": "c8347756-9f86-11ec-8c14-00163e1b6f58", "controlName": "ADD_RANDOM", "controlType": "", "selectIndex": 0, "cmd": "03", "remark": "随机闪烁", "tip": "", "elements": {}, "cmdList": [], "controls": [{"id": 566, "parentId": 562, "uuid": "fecea8ac-9f86-11ec-8c14-00163e1b6f58", "controlName": "OPT_SPEED_ADD", "controlType": "slip", "selectIndex": 0, "cmd": "55", "remark": "速度", "tip": "", "elements": {"max": "100", "min": "1", "step": "1", "item": "50"}, "cmdList": [], "controls": []}]}, {"id": 563, "parentId": 559, "uuid": "ce8fa038-9f86-11ec-8c14-00163e1b6f58", "controlName": "ADD_PULSE", "controlType": "", "selectIndex": 0, "cmd": "04", "remark": "脉冲", "tip": "", "elements": {}, "cmdList": [], "controls": [{"id": 567, "parentId": 563, "uuid": "0c0439e1-9f87-11ec-8c14-00163e1b6f58", "controlName": "OPT_PULSES", "controlType": "slip", "selectIndex": 0, "cmd": "1D", "remark": "脉冲数/分钟", "tip": "", "elements": {"max": "240", "min": "1", "step": "1", "item": "40"}, "cmdList": [], "controls": []}]}]}]}]}]}], "coloredPaper": []}, "msg": "成功"}